setup.cfg
setup.py
contextio/__init__.py
contextio/contextio.py
contextio.egg-info/PKG-INFO
contextio.egg-info/SOURCES.txt
contextio.egg-info/dependency_links.txt
contextio.egg-info/not-zip-safe
contextio.egg-info/requires.txt
contextio.egg-info/top_level.txt
contextio/lib/__init__.py
contextio/lib/api.py
contextio/lib/app.py
contextio/lib/errors.py
contextio/lib/helpers.py
contextio/lib/lite.py
contextio/lib/v2_0.py
contextio/lib/resources/__init__.py
contextio/lib/resources/account.py
contextio/lib/resources/base_resource.py
contextio/lib/resources/connect_token.py
contextio/lib/resources/contact.py
contextio/lib/resources/discovery.py
contextio/lib/resources/email_account.py
contextio/lib/resources/email_address.py
contextio/lib/resources/file.py
contextio/lib/resources/folder.py
contextio/lib/resources/message.py
contextio/lib/resources/oauth_provider.py
contextio/lib/resources/source.py
contextio/lib/resources/thread.py
contextio/lib/resources/user.py
contextio/lib/resources/webhook.py
tests/__init__.py
tests/test_contextio.py
tests/lib/__init__.py
tests/lib/test_api.py
tests/lib/test_app.py
tests/lib/test_helpers.py
tests/lib/test_lite.py
tests/lib/test_v2_0.py
tests/lib/resources/__init__.py
tests/lib/resources/test_account.py
tests/lib/resources/test_base_resource.py
tests/lib/resources/test_connect_token.py
tests/lib/resources/test_contact.py
tests/lib/resources/test_discovery.py
tests/lib/resources/test_email_account.py
tests/lib/resources/test_email_address.py
tests/lib/resources/test_file.py
tests/lib/resources/test_folder.py
tests/lib/resources/test_message.py
tests/lib/resources/test_oauth_provider.py
tests/lib/resources/test_source.py
tests/lib/resources/test_thread.py
tests/lib/resources/test_user.py
tests/lib/resources/test_webhook.py