Metadata-Version: 1.1
Name: contextio
Version: 1.12.8
Summary: Library for accessing the Context.IO API (v2.0 and Lite) in Python
Home-page: http://context.io
Author: Alex Tanton, Cecy Correa
Author-email: alex.tanton@returnpath.com, cecy.correa@returnpath.com
License: UNKNOWN
Download-URL: https://github.com/contextio/Python-ContextIO/archive/v1.12.8.tar.gz
Keywords: contextIO,imap,oauth
Platform: UNKNOWN
